lupin4/__init__.py
lupin4/bundle_dssm.py
lupin4/detector.py
lupin4/dssm.py
lupin4/main.py
lupin4/merge.py
lupin4/metrics.py
lupin4/model.py
lupin4/performance.py
lupin4/plot.py
lupin4/scorecard.py
lupin4/selection.py
lupin4/stats.py
lupin4/transform.py
lupin4/version.py
lupin4/widedeepbinary.py
lupin4/utils/__init__.py
lupin4/utils/backwardSplit.py
lupin4/utils/decorator.py
lupin4/utils/forwardSplit.py
lupin4/utils/func.py
lupin4/utils/mapa.py
lupin4/utils/mixin.py
lupin4/utils/simpleMethods.py
lupin4/utils/trendDiscretization.py
lupin4/utils/trendSplit.py
lupin4-0.0.4.data/data/README.md
lupin4-0.0.4.dist-info/LICENSE
lupin4-0.0.4.dist-info/METADATA
lupin4-0.0.4.dist-info/WHEEL
lupin4-0.0.4.dist-info/top_level.txt
lupin4-0.0.4.dist-info/RECORD
