Metadata-Version: 2.1
Name: lupin4
Version: 0.0.4
Summary: UNKNOWN
Home-page: UNKNOWN
Author: Roryou
License: MIT
Keywords: scorecard,deep learning,wide&deep
Platform: UNKNOWN
Classifier: Operating System :: POSIX
Classifier: Operating System :: Microsoft :: Windows
Classifier: Operating System :: MacOS :: MacOS X
Classifier: Programming Language :: Python :: 3.5
Classifier: Programming Language :: Python :: 3.6
Classifier: Programming Language :: Python :: 3.7
Classifier: Programming Language :: Python :: 3.8
Classifier: Programming Language :: Python :: 3.9
Requires-Python: >=3.5
License-File: LICENSE
